{"_id":"a62bdcde-6ce9-428a-8db8-2347395fbe3f1531891310718","conversation_id":"698954b1-606a-4b09-9a06-29e6f464189d","watson_conversation_id":"a62bdcde-6ce9-428a-8db8-2347395fbe3f","input":"seguro de hogar","intent":[{"intent":"consulta","confidence":0.5927377939224243}],"ramo":"Hogar","arbol":"SEGUROS","output":"\u003clongTail /\u003e \u003cresetConversation /\u003e","codigo_respuesta":"10791,10794,10800,10803,10780,10782,10783,10784,10807,10786,10788,10787,10790,10792,10793","codigo_respuesta_detalle":null,"long_tail":true,"literal":false,"codigos_long_tail":["10791","10794","10800","10803","10780","10782","10783","10784","10807","10786","10788","10787","10790","10792","10793"],"malentendido":null,"chat_source":"CAU","N_Gestor":"N80302","time":{"$date":"2018-07-18T05:21:50.790Z"},"F_cliente":"undefined-undefined"}
{"_id":"497fef7b-8096-4195-877b-510c2bcb0f3b1531891320510","conversation_id":"698954b1-606a-4b09-9a06-29e6f464189d","watson_conversation_id":"497fef7b-8096-4195-877b-510c2bcb0f3b","input":"realizar el pago","intent":[{"intent":"SEGUROS","confidence":0.47312612533569337}],"ramo":null,"arbol":"MASTERTREE","output":"He encontrado varias coincidencias en los siguientes temas, elija al que se refiere: /*insertarBotones(1.- SEGUROS: .1.  realizar el pago ~ 2.- PROPUESTAS:.2.  realizar el pago ~ 3.- MMPP:.3. realizar el pago ~ 4.- CUENTAS_PERSONALES:.4. realizar el pago)*/","codigo_respuesta":null,"codigo_respuesta_detalle":null,"long_tail":null,"literal":false,"codigos_long_tail":null,"malentendido":null,"chat_source":"CAU","N_Gestor":"N80302","time":{"$date":"2018-07-18T05:22:00.536Z"},"F_cliente":"undefined-undefined"}
{"_id":"6a399c17-285a-4aab-a334-66d1a81aa0621531891325749","conversation_id":"698954b1-606a-4b09-9a06-29e6f464189d","watson_conversation_id":"6a399c17-285a-4aab-a334-66d1a81aa062","input":" .1.  realizar el pago ","intent":[{"intent":"consulta","confidence":0.7099399089813232}],"ramo":null,"arbol":"SEGUROS","output":"¿A qué tipo(ramo) se refiere?","codigo_respuesta":null,"codigo_respuesta_detalle":null,"long_tail":null,"literal":false,"codigos_long_tail":null,"malentendido":null,"chat_source":"CAU","N_Gestor":"N80302","time":{"$date":"2018-07-18T05:22:05.771Z"},"F_cliente":"undefined-undefined"}
{"_id":"e381038b-d406-45d6-8c41-ab147836a90b1531891678798","conversation_id":"698954b1-606a-4b09-9a06-29e6f464189d","watson_conversation_id":"e381038b-d406-45d6-8c41-ab147836a90b","input":"hoga","intent":[],"ramo":null,"arbol":"MASTERTREE","output":"Por favor, \u003cb\u003ereformule la pregunta\u003c/b\u003e tratando de especificar en la medida de lo posible el producto o el ramo al que hace referencia.","codigo_respuesta":null,"codigo_respuesta_detalle":null,"long_tail":null,"literal":false,"codigos_long_tail":null,"malentendido":1,"chat_source":"CAU","N_Gestor":"N80302","time":{"$date":"2018-07-18T05:27:58.834Z"},"F_cliente":"undefined-undefined"}
{"_id":"9a13abbd-8b63-482c-a9c4-5212afbe1bb91531891693652","conversation_id":"698954b1-606a-4b09-9a06-29e6f464189d","watson_conversation_id":"9a13abbd-8b63-482c-a9c4-5212afbe1bb9","input":"seguro","intent":[{"intent":"consulta","confidence":0.4634001970291138}],"ramo":null,"arbol":"SEGUROS","output":"¿A qué tipo(ramo) se refiere?","codigo_respuesta":null,"codigo_respuesta_detalle":null,"long_tail":null,"literal":false,"codigos_long_tail":null,"malentendido":null,"chat_source":"CAU","N_Gestor":"N80302","time":{"$date":"2018-07-18T05:28:13.674Z"},"F_cliente":"undefined-undefined"}
{"_id":"9a13abbd-8b63-482c-a9c4-5212afbe1bb91531891696719","conversation_id":"698954b1-606a-4b09-9a06-29e6f464189d","watson_conversation_id":"9a13abbd-8b63-482c-a9c4-5212afbe1bb9","input":"seguro","intent":[{"intent":"consulta","confidence":0.6550874710083008}],"ramo":"Hogar","arbol":"SEGUROS","output":"\u003clongTail /\u003e \u003cresetConversation /\u003e","codigo_respuesta":"10791,10794,10800,10803,10780,10782,10783,10784,10807,10786,10788,10787,10790,10792,10793","codigo_respuesta_detalle":null,"long_tail":true,"literal":false,"codigos_long_tail":["10791","10794","10800","10803","10780","10782","10783","10784","10807","10786","10788","10787","10790","10792","10793"],"malentendido":null,"chat_source":"CAU","N_Gestor":"N80302","time":{"$date":"2018-07-18T05:28:16.742Z"},"F_cliente":"undefined-undefined","openTicket":"10791"}
{"_id":"cc85c87a-8a2a-4e73-857e-905b8211034d1531893828731","conversation_id":"cc85c87a-8a2a-4e73-857e-905b8211034d","watson_conversation_id":"cc85c87a-8a2a-4e73-857e-905b8211034d","input":"tonner  ","intent":[],"ramo":null,"arbol":"MASTERTREE","output":"Por favor, \u003cb\u003ereformule la pregunta\u003c/b\u003e tratando de especificar en la medida de lo posible el producto o el ramo al que hace referencia.","codigo_respuesta":null,"codigo_respuesta_detalle":null,"long_tail":null,"literal":false,"codigos_long_tail":null,"malentendido":1,"chat_source":"CAU","N_Gestor":"N59952","time":{"$date":"2018-07-18T06:03:48.808Z"},"F_cliente":"undefined-undefined"}
{"_id":"cc85c87a-8a2a-4e73-857e-905b8211034d1531893841191","conversation_id":"cc85c87a-8a2a-4e73-857e-905b8211034d","watson_conversation_id":"cc85c87a-8a2a-4e73-857e-905b8211034d","input":"tonner agotado","intent":[],"ramo":null,"arbol":"MASTERTREE","output":"Disculpe, pero \u003cb\u003enecesito más detalles\u003c/b\u003e. Por favor, trate de referirse a un producto, ramo o ámbito concreto, si aplica. Gracias.","codigo_respuesta":null,"codigo_respuesta_detalle":null,"long_tail":null,"literal":false,"codigos_long_tail":null,"malentendido":2,"chat_source":"CAU","N_Gestor":"N59952","time":{"$date":"2018-07-18T06:04:01.239Z"},"F_cliente":"undefined-undefined"}
{"_id":"2552c0c5-7aee-4e50-89f1-a04e973cabad1531893851459","conversation_id":"cc85c87a-8a2a-4e73-857e-905b8211034d","watson_conversation_id":"2552c0c5-7aee-4e50-89f1-a04e973cabad","input":"pedir tonner","intent":[{"intent":"cancelacion","confidence":0.4335902452468872}],"ramo":null,"arbol":"PROPUESTAS","output":"\u003clongTail /\u003e","codigo_respuesta":"24657,24530,24433,24480,24399,24500","codigo_respuesta_detalle":null,"long_tail":true,"literal":false,"codigos_long_tail":["24657","24530","24433","24480","24399","24500"],"malentendido":0,"chat_source":"CAU","N_Gestor":"N59952","time":{"$date":"2018-07-18T06:04:11.486Z"},"F_cliente":"undefined-undefined"}
{"_id":"689c9c96-96ee-4727-bf0b-2d37e8e2ee8f1531894158405","conversation_id":"689c9c96-96ee-4727-bf0b-2d37e8e2ee8f","watson_conversation_id":"689c9c96-96ee-4727-bf0b-2d37e8e2ee8f","input":"envio moneda","intent":[{"intent":"DIGITALIZACION","confidence":0.3214094255352222}],"ramo":null,"arbol":"MASTERTREE","output":"Por favor, \u003cb\u003ereformule la pregunta\u003c/b\u003e tratando de especificar en la medida de lo posible el producto o el ramo al que hace referencia.","codigo_respuesta":null,"codigo_respuesta_detalle":null,"long_tail":null,"literal":false,"codigos_long_tail":null,"malentendido":1,"chat_source":"CAU","N_Gestor":"N36164","time":{"$date":"2018-07-18T06:09:18.488Z"},"F_cliente":"undefined-undefined"}
{"_id":"689c9c96-96ee-4727-bf0b-2d37e8e2ee8f1531894172539","conversation_id":"689c9c96-96ee-4727-bf0b-2d37e8e2ee8f","watson_conversation_id":"689c9c96-96ee-4727-bf0b-2d37e8e2ee8f","input":"moneda extranjera","intent":[],"ramo":null,"arbol":"MASTERTREE","output":"Disculpe, pero \u003cb\u003enecesito más detalles\u003c/b\u003e. Por favor, trate de referirse a un producto, ramo o ámbito concreto, si aplica. Gracias.","codigo_respuesta":null,"codigo_respuesta_detalle":null,"long_tail":null,"literal":false,"codigos_long_tail":null,"malentendido":2,"chat_source":"CAU","N_Gestor":"N36164","time":{"$date":"2018-07-18T06:09:32.561Z"},"F_cliente":"undefined-undefined"}
{"_id":"9eb02f42-a02a-4062-bfc8-1fb0a84fc2031531894918446","conversation_id":"7b424aee-48c5-40c9-b677-aa6df19c4959","watson_conversation_id":"9eb02f42-a02a-4062-bfc8-1fb0a84fc203","input":"alta sistema analisis personas fisicas","intent":[{"intent":"contratacion","confidence":0.9060941696166993}],"ramo":null,"arbol":"PROPUESTAS","output":"\u003clongTail /\u003e","codigo_respuesta":"24879,24860,24899,24689,24859,21675,24692,24433","codigo_respuesta_detalle":null,"long_tail":true,"literal":false,"codigos_long_tail":["24879","24860","24899","24689","24859","21675","24692","24433"],"malentendido":null,"chat_source":"CAU","N_Gestor":"N56462","time":{"$date":"2018-07-18T06:21:58.516Z"},"F_cliente":"undefined-undefined"}
{"_id":"f45de21f-ecf4-456d-a1ab-a9b9c745e3961531895491223","conversation_id":"1a3e670a-b6dd-4da9-87b4-700f2cd3804e","watson_conversation_id":"f45de21f-ecf4-456d-a1ab-a9b9c745e396","input":"como se obtiene codigo lei","intent":[{"intent":"LEI","confidence":0.9530653476715087}],"ramo":null,"arbol":"MIFID","output":"\u003cshortTail id='20087' opcion='main' /\u003e \u003cresetConversation /\u003e","codigo_respuesta":"20087","codigo_respuesta_detalle":"main","long_tail":false,"literal":false,"codigos_long_tail":null,"malentendido":null,"chat_source":"CAU","N_Gestor":"N23036","time":{"$date":"2018-07-18T06:31:31.248Z"},"F_cliente":"undefined-undefined"}
{"_id":"7c79ced2-075d-4efa-b223-2b47a28a71c21531895823020","conversation_id":"7c79ced2-075d-4efa-b223-2b47a28a71c2","watson_conversation_id":"7c79ced2-075d-4efa-b223-2b47a28a71c2","input":"certificado de posiciones","intent":[{"intent":"TESTAMENTARIA","confidence":0.6803852081298829}],"ramo":null,"arbol":"MASTERTREE","output":"He encontrado varias coincidencias en los siguientes temas, elija al que se refiere:  /*insertarBotones(1.- TESTAMENTARIA:.1. certificado de posiciones ~ 2.- CUENTAS_PERSONALES:.2. certificado de posiciones)*/","codigo_respuesta":null,"codigo_respuesta_detalle":null,"long_tail":null,"literal":false,"codigos_long_tail":null,"malentendido":null,"chat_source":"CAU","N_Gestor":"N36884","time":{"$date":"2018-07-18T06:37:03.093Z"},"F_cliente":"undefined-undefined"}
{"_id":"4d221d9a-9b07-42ea-8803-58e9698d0b301531895826385","conversation_id":"7c79ced2-075d-4efa-b223-2b47a28a71c2","watson_conversation_id":"4d221d9a-9b07-42ea-8803-58e9698d0b30","input":".1. certificado de posiciones ","intent":[],"ramo":null,"arbol":"TESTAMENTARIA","output":"\u003clongTail /\u003e","codigo_respuesta":"4706,4705,4713,20072,19800,19801,4704,4714,4709,4707,4710,4708,20073,21225,4692","codigo_respuesta_detalle":null,"long_tail":true,"literal":false,"codigos_long_tail":["4706","4705","4713","20072","19800","19801","4704","4714","4709","4707","4710","4708","20073","21225","4692"],"malentendido":null,"chat_source":"CAU","N_Gestor":"N36884","time":{"$date":"2018-07-18T06:37:06.409Z"},"F_cliente":"undefined-undefined","openTicket":"4706"}
{"_id":"ab12edf1-33cf-4ed1-a0f3-cd3e107332c61531896246844","conversation_id":"4bdb9270-9216-48c4-b6bb-908d2b27cbb1","watson_conversation_id":"ab12edf1-33cf-4ed1-a0f3-cd3e107332c6","input":"seguridad y control","intent":[{"intent":"consulta","confidence":0.953007173538208}],"ramo":null,"arbol":"123","output":"\u003cshortTail id='7736' opcion='main' /\u003e \u003cresetConversation /\u003e","codigo_respuesta":"7736","codigo_respuesta_detalle":"main","long_tail":false,"literal":false,"codigos_long_tail":null,"malentendido":null,"chat_source":"CAU","N_Gestor":"XI329739","time":{"$date":"2018-07-18T06:44:06.872Z"},"F_cliente":"undefined-undefined"}
{"_id":"1f39b555-ae43-4710-bf77-655ebd5ce58c1531896269256","conversation_id":"4bdb9270-9216-48c4-b6bb-908d2b27cbb1","watson_conversation_id":"1f39b555-ae43-4710-bf77-655ebd5ce58c","input":"otro tema","intent":[],"ramo":null,"arbol":"MASTERTREE","output":"Por favor, \u003cb\u003ereformule la pregunta\u003c/b\u003e tratando de especificar en la medida de lo posible el producto o el ramo al que hace referencia.","codigo_respuesta":null,"codigo_respuesta_detalle":null,"long_tail":null,"literal":false,"codigos_long_tail":null,"malentendido":1,"chat_source":"CAU","N_Gestor":"XI329739","time":{"$date":"2018-07-18T06:44:29.291Z"},"F_cliente":"undefined-undefined"}
{"_id":"19046678-595f-4ed9-baa2-c61bf71cd6bd1531896275740","conversation_id":"4bdb9270-9216-48c4-b6bb-908d2b27cbb1","watson_conversation_id":"19046678-595f-4ed9-baa2-c61bf71cd6bd","input":"el regalo va ligado a la poliza","intent":[{"intent":"consulta","confidence":0.3763033032417298}],"ramo":null,"arbol":"SEGUROS","output":"¿A qué tipo(ramo) se refiere?","codigo_respuesta":null,"codigo_respuesta_detalle":null,"long_tail":null,"literal":false,"codigos_long_tail":null,"malentendido":null,"chat_source":"CAU","N_Gestor":"XI329739","time":{"$date":"2018-07-18T06:44:35.768Z"},"F_cliente":"undefined-undefined"}
{"_id":"19046678-595f-4ed9-baa2-c61bf71cd6bd1531896279947","conversation_id":"4bdb9270-9216-48c4-b6bb-908d2b27cbb1","watson_conversation_id":"19046678-595f-4ed9-baa2-c61bf71cd6bd","input":"el regalo va ligado a la poliza","intent":[{"intent":"consulta","confidence":0.7670392990112305}],"ramo":"Vida","arbol":"SEGUROS","output":"\u003clongTail /\u003e \u003cresetConversation /\u003e","codigo_respuesta":"11802,12022,11970,11769,11756,11770,11771,11754,12024,11801,11988,11724,11726,11821,11723","codigo_respuesta_detalle":null,"long_tail":true,"literal":false,"codigos_long_tail":["11802","12022","11970","11769","11756","11770","11771","11754","12024","11801","11988","11724","11726","11821","11723"],"malentendido":null,"chat_source":"CAU","N_Gestor":"XI329739","time":{"$date":"2018-07-18T06:44:39.971Z"},"F_cliente":"undefined-undefined"}
{"_id":"f76c93f4-1af5-4d55-ad53-c585f05fe25a1531896286234","conversation_id":"4bdb9270-9216-48c4-b6bb-908d2b27cbb1","watson_conversation_id":"f76c93f4-1af5-4d55-ad53-c585f05fe25a","input":"otro tema","intent":[],"ramo":null,"arbol":"MASTERTREE","output":"Por favor, \u003cb\u003ereformule la pregunta\u003c/b\u003e tratando de especificar en la medida de lo posible el producto o el ramo al que hace referencia.","codigo_respuesta":null,"codigo_respuesta_detalle":null,"long_tail":null,"literal":false,"codigos_long_tail":null,"malentendido":1,"chat_source":"CAU","N_Gestor":"XI329739","time":{"$date":"2018-07-18T06:44:46.265Z"},"F_cliente":"undefined-undefined"}
